setup.py
sulphite/__init__.py
sulphite/cli.py
sulphite.egg-info/PKG-INFO
sulphite.egg-info/SOURCES.txt
sulphite.egg-info/dependency_links.txt
sulphite.egg-info/entry_points.txt
sulphite.egg-info/requires.txt
sulphite.egg-info/top_level.txt