Metadata-Version: 1.0
Name: sulphite
Version: 1.0.0
Summary: Library & Eventlistener for Supervisord to send events to Graphite
Home-page: https://github.com/jib/sulphite
Author: Jos Boumans
Author-email: jos@dwim.org
License: UNKNOWN
Platform: UNKNOWN
